chk/__init__.py
chk/__main__.py
chk/console/main.py
chk/console/services.py
chk/infrastructure/document.py
chk/infrastructure/file_loader.py
chk/infrastructure/helper.py
chk/infrastructure/logging.py
chk/infrastructure/symbol_table.py
chk/infrastructure/templating.py
chk/infrastructure/typing_extras.py
chk/infrastructure/version.py
chk/infrastructure/view.py
chk/modules/fetch/__init__.py
chk/modules/fetch/entities.py
chk/modules/fetch/services.py
chk/modules/validate/__init__.py
chk/modules/validate/assertion_function.py
chk/modules/validate/assertion_message.py
chk/modules/validate/assertion_services.py
chk/modules/validate/assertion_validation.py
chk/modules/validate/entities.py
chk/modules/validate/services.py
chk/modules/workflow/__init__.py
chk/modules/workflow/entities.py
chk/modules/workflow/services.py
chk-0.5.0.dist-info/LICENSE
chk-0.5.0.dist-info/METADATA
chk-0.5.0.dist-info/WHEEL
chk-0.5.0.dist-info/entry_points.txt
chk-0.5.0.dist-info/RECORD
