Metadata-Version: 2.1
Name: chk
Version: 0.5.0
Summary: Low-code API quality testing, and automation toolbox
Home-page: https://chkware.com/
License: MPL-2.0
Author: Mahmudul Hasan
Author-email: hasanlock@gmail.com
Requires-Python: >=3.13,<4.0
Classifier: Development Status :: 4 - Beta
Classifier: Environment :: Console
Classifier: Intended Audience :: Information Technology
Classifier: License :: OSI Approved
Classifier: License :: OSI Approved :: Mozilla Public License 2.0 (MPL 2.0)
Classifier: Operating System :: MacOS
Classifier: Operating System :: Microsoft
Classifier: Operating System :: POSIX :: Linux
Classifier: Programming Language :: Python :: 3
Classifier: Programming Language :: Python :: 3.13
Classifier: Topic :: Internet :: WWW/HTTP
Classifier: Topic :: Software Development
Classifier: Topic :: Software Development :: Quality Assurance
Classifier: Topic :: Software Development :: Testing
Classifier: Topic :: System :: Networking
Classifier: Topic :: Terminals
Classifier: Topic :: Text Processing
Classifier: Topic :: Utilities
Requires-Dist: cerberus (>=1.3.5,<2.0.0)
Requires-Dist: click (>=8.1.7,<9.0.0)
Requires-Dist: defusedxml (>=0.7.1,<0.8.0)
Requires-Dist: jinja2 (>=3.1.4,<4.0.0)
Requires-Dist: loguru (>=0.7.3,<0.8.0)
Requires-Dist: pydantic (>=2.10.4,<3.0.0)
Requires-Dist: python-dotenv (>=1.0.1,<2.0.0)
Requires-Dist: pyyaml (>=6.0.2,<7.0.0)
Requires-Dist: requests (>=2.32.3,<3.0.0)
Requires-Dist: xmltodict (>=0.14.2,<0.15.0)
Project-URL: Ask a question, https://github.com/orgs/chkware/discussions/categories/q-a
Project-URL: Bug Tracker, https://github.com/chkware/cli/issues
Project-URL: Documentation, https://chkware.com/docs
Project-URL: Repository, https://github.com/chkware/cli
Project-URL: Twitter, https://twitter.com/chkware
